py2gc/__init__.py
py2gc/api_call.py
py2gc/parsers.py
py2gc/py2gc.py
py2gc-1.0.6.dist-info/LICENSE
py2gc-1.0.6.dist-info/METADATA
py2gc-1.0.6.dist-info/WHEEL
py2gc-1.0.6.dist-info/entry_points.txt
py2gc-1.0.6.dist-info/top_level.txt
py2gc-1.0.6.dist-info/RECORD
