Metadata-Version: 2.1
Name: py2gc
Version: 1.0.6
Summary: Add events to a Google Calendar from the command line.
Home-page: https://github.com/stefanpf/py2gc
Author: Stefan Pfeuffer
Author-email: mail@stefanpfeuffer.com
License: MIT
Platform: UNKNOWN
Classifier: Programming Language :: Python :: 3
Classifier: License :: OSI Approved :: MIT License
Classifier: Operating System :: OS Independent
Requires-Dist: httplib2
Requires-Dist: argparse
Requires-Dist: oauth2client
Requires-Dist: google-api-python-client
Requires-Dist: pathlib
